drydock/__about__.py
drydock/__init__.py
drydock/hooks.py
drydock/patches/.gitignore
drydock/patches/caddyfile
drydock/patches/caddyfile-cms
drydock/patches/caddyfile-lms
drydock/patches/cms-env
drydock/patches/k8s-jobs
drydock/patches/kustomization
drydock/patches/kustomization-configmapgenerator
drydock/patches/kustomization-resources
drydock/patches/lms-env
drydock/patches/openedx-common-settings
drydock/patches/static-cache-config
drydock/patches/uwsgi-config
drydock/plugin.py
drydock/templates/drydock/k8s/debug/deployments.yml
drydock/templates/drydock/k8s/debug/ingress.yml
drydock/templates/drydock/k8s/debug/services.yml
drydock/templates/drydock/k8s/ingress/cms.yml
drydock/templates/drydock/k8s/ingress/extra-hosts.yml
drydock/templates/drydock/k8s/ingress/issuer.yml
drydock/templates/drydock/k8s/ingress/lms.yml
drydock/templates/drydock/k8s/ingress/meilisearch.yml
drydock/templates/drydock/k8s/ingress/mfe.yml
drydock/templates/drydock/k8s/ingress/notes.yml
drydock/templates/drydock/k8s/ingress/static-cache.yml
drydock/templates/drydock/k8s/jobs.yml
drydock/templates/drydock/k8s/lifecycle/cms.yml
drydock/templates/drydock/k8s/lifecycle/lms.yml
drydock/templates/drydock/k8s/multipurpose-jobs.yml
drydock/templates/drydock/k8s/newrelic.ini
drydock/templates/drydock/k8s/newrelic.yml
drydock/templates/drydock/k8s/patches/add-image-pull-secret-cronjob.yml
drydock/templates/drydock/k8s/patches/add-image-pull-secret.yml
drydock/templates/drydock/k8s/patches/hpa-sync-wave.yml
drydock/templates/drydock/k8s/patches/post-init-deployments-sync-wave.yml
drydock/templates/drydock/k8s/patches/tutor-jobs.yml
drydock/templates/drydock/k8s/pdb/openedx-pdb.yml
drydock/templates/drydock/k8s/secrets/image-pull-secret.yml
drydock/templates/drydock/task/mongodb/init
tutor_contrib_drydock-20.1.1.dist-info/WHEEL
tutor_contrib_drydock-20.1.1.dist-info/entry_points.txt
tutor_contrib_drydock-20.1.1.dist-info/METADATA
tutor_contrib_drydock-20.1.1.dist-info/RECORD
