Metadata-Version: 2.3
Name: tutor-contrib-drydock
Version: 20.1.1
Summary: A Tutor plugin to manage our opinionated Open edX operations
Author: eduNEXT
License:                     GNU AFFERO GENERAL PUBLIC LICENSE
Classifier: Development Status :: 3 - Alpha
Classifier: Intended Audience :: Developers
Classifier: License :: OSI Approved :: GNU Affero General Public License v3
Classifier: Operating System :: OS Independent
Classifier: Programming Language :: Python
Classifier: Programming Language :: Python :: 3.10
Classifier: Programming Language :: Python :: 3.11
Classifier: Programming Language :: Python :: 3.12
Classifier: Programming Language :: Python :: 3.13
Requires-Dist: tutor~=20.0
Requires-Python: >=3.10
Project-URL: Code, https://github.com/edunext/drydock
Project-URL: Homepage, https://github.com/edunext/drydock
Project-URL: Issue tracker, https://github.com/edunext/drydock/issues
